infolingo/__init__.py
infolingo/infolingo.py
infolingo/main.py
infolingo/data/fra_news_2023_300K-words.csv
infolingo/data/sample1.csv
infolingo/data/sample2.csv
infolingo-1.1.0.dist-info/LICENSE
infolingo-1.1.0.dist-info/METADATA
infolingo-1.1.0.dist-info/WHEEL
infolingo-1.1.0.dist-info/top_level.txt
infolingo-1.1.0.dist-info/RECORD
