Metadata-Version: 2.1
Name: infolingo
Version: 1.1.0
Summary: Efficient Vocabulary Selection for Foreign-Language Learning.
Author-email: Alice Heiman <aheiman@stanford.edu>
Classifier: Programming Language :: Python :: 3
Classifier: License :: OSI Approved :: MIT License
Classifier: Operating System :: OS Independent
Requires-Python: >=3.8
License-File: LICENSE
Requires-Dist: pytest
Requires-Dist: nltk
